AGLOW/__init__.py
AGLOW/version.py
AGLOW/airflow/__init__.py
AGLOW/airflow/dags/__init__.py
AGLOW/airflow/operators/LRT_Sandbox.py
AGLOW/airflow/operators/LRT_storage_to_srm.py
AGLOW/airflow/operators/LRT_submit.py
AGLOW/airflow/operators/LRT_token.py
AGLOW/airflow/operators/LTA_staging.py
AGLOW/airflow/operators/__init__.py
AGLOW/airflow/operators/data_staged.py
AGLOW/airflow/operators/lofar_staging.py
AGLOW/airflow/sensors/__init__.py
AGLOW/airflow/sensors/glite_wms_sensor.py
AGLOW/airflow/subdags/SKSP_calibrator.py
AGLOW/airflow/subdags/SKSP_juelich.py
AGLOW/airflow/subdags/SKSP_target.py
AGLOW/airflow/subdags/__init__.py
AGLOW/airflow/utils/AGLOW_MySQL_utils.py
AGLOW/airflow/utils/AGLOW_utils.py
AGLOW/airflow/utils/__init__.py
AGLOW-0.0.9.9.dist-info/DESCRIPTION.rst
AGLOW-0.0.9.9.dist-info/METADATA
AGLOW-0.0.9.9.dist-info/RECORD
AGLOW-0.0.9.9.dist-info/WHEEL
AGLOW-0.0.9.9.dist-info/metadata.json
AGLOW-0.0.9.9.dist-info/top_level.txt
