Metadata-Version: 2.0
Name: AGLOW
Version: 0.0.9.9
Summary: AGLOW: Automated Grid-enabled LOFAR Workflows
Home-page: https://www.github.com/apmechev/AGLOW/
Author: Alexandar Mechev
Author-email: LOFAR@apmechev.com
License: UNKNOWN
Download-URL: https://github.com/apmechev/AGLOW/archive/v0.0.9x.tar.gz
Keywords: surfsara,distributed-computing,LOFAR,workflow,airflow
Platform: UNKNOWN
Classifier: Development Status :: 2 - Pre-Alpha
Classifier: Intended Audience :: Developers
Classifier: Intended Audience :: Science/Research
Classifier: License :: OSI Approved :: GNU General Public License v3 (GPLv3)
Classifier: Natural Language :: English
Classifier: Topic :: Scientific/Engineering :: Astronomy
Classifier: Topic :: System :: Distributed Computing
Classifier: Programming Language :: Python :: 2.6
Classifier: Programming Language :: Python :: 2.7
Classifier: Programming Language :: Python :: 3
Classifier: Programming Language :: Python :: 3.2
Classifier: Programming Language :: Python :: 3.3
Classifier: Programming Language :: Python :: 3.4
Requires-Dist: GRID-LRT
Requires-Dist: apache-airflow
Requires-Dist: six
Requires-Dist: snakebite
Requires-Dist: tzlocal (==1.5.1)
